{
  "dock": "null",
  "sun": {
    "next_sunrise": "06:31",
    "next_sunset": "17:28"
  },
  "time": "2025-02-21T19:30:00.086107-05:00",
  "weather": {
    "attribution": "Weather data delivered by WeatherFlow/Tempest REST Api",
    "dew_point": 12,
    "friendly_name": "Raymonds Point",
    "humidity": 54,
    "precipitation_unit": "in",
    "pressure": 29.84,
    "pressure_unit": "inHg",
    "supported_features": 3,
    "temperature": 27,
    "temperature_unit": "°F",
    "uv_index": 0,
    "visibility_unit": "mi",
    "wind_bearing": 288,
    "wind_gust_speed": 4.47,
    "wind_speed": 2.24,
    "wind_speed_unit": "mph"
  },
  "weather_station": {
    "feels_like": 26.9,
    "lightning_average_distance": 0,
    "precipitation_type": "none",
    "temperature": 26.9,
    "uv_index": 0,
    "wind_direction": 240,
    "wind_direction_average": 203,
    "wind_gust": "3.71",
    "wind_speed_average": 1.77
  }
}
