{
  "dock": {
    "temperature": 41.7,
    "temperature_unit": "°F",
    "water_level": 0,
    "water_level_unit": "ft"
  },
  "sun": {
    "next_sunrise": "07:07",
    "next_sunset": "17:45"
  },
  "time": "2025-03-08T14:15:00.085867-05:00",
  "weather": {
    "attribution": "Weather data delivered by WeatherFlow/Tempest REST Api",
    "dew_point": 14,
    "friendly_name": "Raymonds Point",
    "humidity": 33,
    "precipitation_unit": "in",
    "pressure": 29.18,
    "pressure_unit": "inHg",
    "supported_features": 3,
    "temperature": 41,
    "temperature_unit": "°F",
    "uv_index": 2,
    "visibility_unit": "mi",
    "wind_bearing": 252,
    "wind_gust_speed": 6.71,
    "wind_speed": 4.47,
    "wind_speed_unit": "mph"
  },
  "weather_station": {
    "feels_like": 37.7,
    "lightning_average_distance": 0,
    "precipitation_type": "none",
    "temperature": 41.3,
    "uv_index": 2,
    "wind_direction": 284,
    "wind_direction_average": 261,
    "wind_gust": "9.62",
    "wind_speed_average": 5.37
  }
}
